[{"__type__":"cc.SpriteFrame","content":{"name":"z0008","texture":"10lqRRA4FCiqQcnnDFev6O","rect":[252,2,48,60],"offset":[0,0],"originalSize":[60,60]}},{"__type__":"cc.AnimationClip","_name":"heroRun","_duration":0.6,"sample":10,"speed":2,"wrapMode":2,"curveData":{"comps":{"cc.Sprite":{"spriteFrame":[{"frame":0,"value":{"__uuid__":"f6MIpWhbVEvaCRjEFJiyrh"}},{"frame":0.2,"value":{"__uuid__":"da3nNeHMlMsJ2M7Wa/NjjA"}},{"frame":0.5,"value":{"__uuid__":"7clklWP3FGmJavCAEqEgIs"}}]}}}},{"__type__":"cc.SpriteFrame","content":{"name":"z0004","texture":"10lqRRA4FCiqQcnnDFev6O","rect":[102,2,48,60],"offset":[0,0],"originalSize":[60,60]}},{"__type__":"cc.SpriteFrame","content":{"name":"z0001","texture":"10lqRRA4FCiqQcnnDFev6O","rect":[302,2,48,58],"offset":[0,0],"originalSize":[60,60]}}]