[[{"__type__":"cc.Prefab","_name":"skill_zhadan","data":{"__id__":1}},{"__type__":"cc.Node","_name":"skill_zhadan","_children":[{"__id__":2}],"_components":[{"__type__":"cc.Sprite","node":{"__id__":1}},{"__type__":"cc.CircleCollider","node":{"__id__":1},"_radius":60},{"__type__":"f2febCXZR1EhZmCSZ1hNeci","node":{"__id__":1},"skillContext":{"__uuid__":"bdsddKmNlP+L8yuvSeHb8U"}}],"_prefab":{"__type__":"cc.PrefabInfo","root":{"__id__":1},"asset":{"__uuid__":"8fpfu4JelK/JPQQ1I4OV+D"},"fileId":"e61SnCgq9IZJs0h5EJZLeN"},"_contentSize":{"__type__":"cc.Size","width":132,"height":132},"_position":{"__type__":"cc.Vec3","y":-109},"_scaleX":0.4,"_scaleY":0.4,"_scale":{"__type__":"cc.Vec3","x":1,"y":1,"z":1},"groupIndex":3},{"__type__":"cc.Node","_name":"Label","_parent":{"__id__":1},"_components":[{"__type__":"cc.Label","node":{"__id__":2},"_useOriginalSize":false,"_string":"炸弹","_N$string":"炸弹","_N$horizontalAlign":1,"_N$verticalAlign":1}],"_prefab":{"__type__":"cc.PrefabInfo","root":{"__id__":1},"asset":{"__uuid__":"8fpfu4JelK/JPQQ1I4OV+D"},"fileId":"11ZERje41H+r9hKeiiqbPv"},"_contentSize":{"__type__":"cc.Size","width":80,"height":40},"_scaleX":1,"_scaleY":1,"_scale":{"__type__":"cc.Vec3","x":1,"y":1,"z":1}}],[{"__type__":"cc.Prefab","_name":"zhadan","data":{"__id__":1}},{"__type__":"cc.Node","_name":"zhadan","_components":[{"__type__":"cc.Sprite","node":{"__id__":1}},{"__type__":"cc.CircleCollider","node":{"__id__":1},"_radius":65},{"__type__":"e26f98/hZZLKY9nOTC0QO8x","node":{"__id__":1}}],"_prefab":{"__type__":"cc.PrefabInfo","root":{"__id__":1},"asset":{"__id__":0},"fileId":"23QI09HElNDY8vuWcsi2tv"},"_contentSize":{"__type__":"cc.Size","width":132,"height":132},"_scaleX":1,"_scaleY":1,"_scale":{"__type__":"cc.Vec3","x":1,"y":1,"z":1},"groupIndex":4}]]